[
  {
    "domestic": true,
    "flight_type": "DIRECT",
    "is_cancelable": true,
    "originSegment": {
      "legs": [
        {
          "arrival_airport_id": 676,
          "departure_airport_id": 320,
          "fromDate": {
            "year": 2021,
            "month": 5,
            "day": 5,
            "minute": 0,
            "hour": 5,
            "date_id": 1620979215318
          },
          "toDate": {
            "year": 2021,
            "month": 5,
            "day": 5,
            "minute": 0,
            "hour": 21,
            "date_id": 1621036815318
          }
        }
      ],
      "baggage": { "weight": 23, "weight_unit": "KG", "included": false },
      "flight_duration": 16
    },
    "destinationSegment": {
      "legs": [
        {
          "arrival_airport_id": 320,
          "departure_airport_id": 676,
          "fromDate": {
            "year": 2021,
            "month": 5,
            "day": 5,
            "minute": 0,
            "hour": 21,
            "date_id": 1621036815318
          },
          "toDate": {
            "year": 2021,
            "month": 5,
            "day": 6,
            "minute": 0,
            "hour": 2,
            "date_id": 1621054815318
          }
        }
      ],
      "baggage": { "weight": 23, "weight_unit": "KG", "included": false },
      "flight_duration": 5
    }
  },
  {
    "domestic": true,
    "flight_type": "DIRECT",
    "is_cancelable": true,
    "originSegment": {
      "legs": [
        {
          "arrival_airport_id": 942,
          "departure_airport_id": 281,
          "fromDate": {
            "year": 2020,
            "month": 6,
            "day": 6,
            "minute": 46,
            "hour": 14,
            "date_id": 1593280005799
          },
          "toDate": {
            "year": 2020,
            "month": 6,
            "day": 1,
            "minute": 46,
            "hour": 4,
            "date_id": 1593416805799
          }
        }
      ],
      "baggage": { "weight": 23, "weight_unit": "KG", "included": false },
      "flight_duration": 38
    },
    "destinationSegment": {
      "legs": [
        {
          "arrival_airport_id": 281,
          "departure_airport_id": 942,
          "fromDate": {
            "year": 2020,
            "month": 6,
            "day": 1,
            "minute": 46,
            "hour": 4,
            "date_id": 1593416805799
          },
          "toDate": {
            "year": 2020,
            "month": 7,
            "day": 3,
            "minute": 46,
            "hour": 13,
            "date_id": 1593622005799
          }
        }
      ],
      "baggage": { "weight": 23, "weight_unit": "KG", "included": false },
      "flight_duration": 57
    }
  },
  {
    "domestic": true,
    "flight_type": "DIRECT",
    "is_cancelable": true,
    "originSegment": {
      "legs": [
        {
          "arrival_airport_id": 180,
          "departure_airport_id": 709,
          "fromDate": {
            "year": 2021,
            "month": 7,
            "day": 1,
            "minute": 51,
            "hour": 14,
            "date_id": 1626717084225
          },
          "toDate": {
            "year": 2021,
            "month": 7,
            "day": 2,
            "minute": 51,
            "hour": 8,
            "date_id": 1626781884225
          }
        }
      ],
      "baggage": { "weight": 23, "weight_unit": "KG", "included": true },
      "flight_duration": 18
    },
    "destinationSegment": {
      "legs": [
        {
          "arrival_airport_id": 709,
          "departure_airport_id": 180,
          "fromDate": {
            "year": 2021,
            "month": 7,
            "day": 2,
            "minute": 51,
            "hour": 8,
            "date_id": 1626781884225
          },
          "toDate": {
            "year": 2021,
            "month": 7,
            "day": 4,
            "minute": 51,
            "hour": 8,
            "date_id": 1626954684225
          }
        }
      ],
      "baggage": { "weight": 23, "weight_unit": "KG", "included": false },
      "flight_duration": 48
    }
  },
  {
    "domestic": true,
    "flight_type": "NON_DIRECT",
    "is_cancelable": true,
    "originSegment": {
      "legs": [
        {
          "arrival_airport_id": 562,
          "departure_airport_id": 444,
          "fromDate": {
            "year": 2020,
            "month": 11,
            "day": 4,
            "minute": 55,
            "hour": 18,
            "date_id": 1604613316455
          },
          "toDate": {
            "year": 2020,
            "month": 11,
            "day": 6,
            "minute": 25,
            "hour": 1,
            "date_id": 1604723116455
          }
        },
        {
          "arrival_airport_id": 88,
          "departure_airport_id": 562,
          "fromDate": {
            "year": 2020,
            "month": 11,
            "day": 4,
            "minute": 55,
            "hour": 18,
            "date_id": 1604613316455
          },
          "toDate": {
            "year": 2020,
            "month": 11,
            "day": 0,
            "minute": 55,
            "hour": 7,
            "date_id": 1604832916455
          }
        },
        {
          "arrival_airport_id": 311,
          "departure_airport_id": 88,
          "fromDate": {
            "year": 2020,
            "month": 11,
            "day": 4,
            "minute": 55,
            "hour": 18,
            "date_id": 1604613316455
          },
          "toDate": {
            "year": 2020,
            "month": 11,
            "day": 1,
            "minute": 25,
            "hour": 14,
            "date_id": 1604942716455
          }
        }
      ],
      "baggage": { "weight": 23, "weight_unit": "KG", "included": false },
      "flight_duration": 61
    },
    "destinationSegment": {
      "legs": [
        {
          "arrival_airport_id": 444,
          "departure_airport_id": 311,
          "fromDate": {
            "year": 2020,
            "month": 11,
            "day": 1,
            "minute": 25,
            "hour": 14,
            "date_id": 1604942716455
          },
          "toDate": {
            "year": 2020,
            "month": 11,
            "day": 1,
            "minute": 25,
            "hour": 22,
            "date_id": 1604971516455
          }
        }
      ],
      "baggage": { "weight": 23, "weight_unit": "KG", "included": false },
      "flight_duration": 8
    }
  },
  {
    "domestic": true,
    "flight_type": "DIRECT",
    "is_cancelable": true,
    "originSegment": {
      "legs": [
        {
          "arrival_airport_id": 593,
          "departure_airport_id": 619,
          "fromDate": {
            "year": 2020,
            "month": 3,
            "day": 5,
            "minute": 14,
            "hour": 13,
            "date_id": 1584720861395
          },
          "toDate": {
            "year": 2020,
            "month": 3,
            "day": 0,
            "minute": 14,
            "hour": 6,
            "date_id": 1584868461395
          }
        }
      ],
      "baggage": { "weight": 23, "weight_unit": "KG", "included": false },
      "flight_duration": 41
    },
    "destinationSegment": {
      "legs": [
        {
          "arrival_airport_id": 619,
          "departure_airport_id": 593,
          "fromDate": {
            "year": 2020,
            "month": 3,
            "day": 0,
            "minute": 14,
            "hour": 6,
            "date_id": 1584868461395
          },
          "toDate": {
            "year": 2020,
            "month": 3,
            "day": 0,
            "minute": 14,
            "hour": 13,
            "date_id": 1584893661395
          }
        }
      ],
      "baggage": { "weight": 23, "weight_unit": "KG", "included": false },
      "flight_duration": 7
    }
  }
]
